fetch_github_issues/__init__.py
fetch_github_issues/__main__.py
fetch_github_issues/cli.py
fetch_github_issues-0.1.2.dist-info/LICENSE
fetch_github_issues-0.1.2.dist-info/METADATA
fetch_github_issues-0.1.2.dist-info/WHEEL
fetch_github_issues-0.1.2.dist-info/entry_points.txt
fetch_github_issues-0.1.2.dist-info/top_level.txt
fetch_github_issues-0.1.2.dist-info/RECORD
