Metadata-Version: 2.1
Name: fetch-github-issues
Version: 0.1.2
Summary: Fetch all GitHub issues for a repository and save them as JSON
Author: Simon Willison
License: Apache-2.0
Project-URL: Homepage, https://github.com/simonw/fetch-github-issues
Project-URL: Changelog, https://github.com/simonw/fetch-github-issues/releases
Project-URL: Issues, https://github.com/simonw/fetch-github-issues/issues
Project-URL: CI, https://github.com/simonw/fetch-github-issues/actions
Classifier: License :: OSI Approved :: Apache Software License
Requires-Python: >=3.8
License-File: LICENSE
Provides-Extra: test
Requires-Dist: pytest ; extra == 'test'
